echolog/__init__.py
echolog/logger.py
pyecholog-3.0.5.dist-info/licenses/LICENSE
pyecholog-3.0.5.dist-info/METADATA
pyecholog-3.0.5.dist-info/WHEEL
pyecholog-3.0.5.dist-info/top_level.txt
pyecholog-3.0.5.dist-info/RECORD
