Metadata-Version: 2.4
Name: pyecholog
Version: 3.0.5
Summary: Lightweight, file-backed logger with colored console output
Author-email: Aymene Boudali <boudaliaymene4@example.com>
License: MIT
Classifier: Programming Language :: Python :: 3
Classifier: License :: OSI Approved :: MIT License
Classifier: Operating System :: OS Independent
Requires-Python: >=3.8
License-File: LICENSE
Requires-Dist: colorama>=0.4.0
Dynamic: license-file
